{
  "naicsCodes": "541613,541820",
  "defaultSectorId": "digital-and-print-media",
  "canHavePermanentLocation": true,
  "roadmapSteps": [
    {
      "step": 1,
      "weight": 1,
      "task": "business-plan"
    },
    {
      "step": 1,
      "weight": 50,
      "task": "determine-naics-code",
      "required": true
    },
    {
      "step": 1,
      "weight": 100,
      "task": "business-structure",
      "required": true
    },
    {
      "step": 2,
      "weight": 20,
      "task": "register-for-ein",
      "required": true
    },
    {
      "step": 2,
      "weight": 25,
      "task": "register-for-taxes",
      "required": true
    },
    {
      "step": 3,
      "weight": 10,
      "task": "bank-account"
    },
    {
      "step": 3,
      "weight": 15,
      "task": "get-insurance"
    }
  ],
  "name": "Marketing and PR Consulting",
  "nonEssentialQuestionsIds": [],
  "displayname": "marketing-pr-consulting",
  "industryOnboardingQuestions": {
    "canBeHomeBased": true,
    "isProvidesStaffingServicesApplicable": true
  },
  "isEnabled": true,
  "additionalSearchTerms": "marketing, advertising, consultant, press, communications, Image management, consultant, advertising, communications, media, promotions",
  "id": "marketing-pr-consulting",
  "description": "Expert advice to improve the client's business exposure",
  "webflowId": "656a1362d61cbaa67af3ac81"
}
